ivp/__init__.py
ivp/ivp.pyd
ivp_rs-0.1.2.dist-info/METADATA
ivp_rs-0.1.2.dist-info/WHEEL
ivp_rs-0.1.2.dist-info/licenses/LICENSE
ivp_rs-0.1.2.dist-info/RECORD
