Metadata-Version: 2.4
Name: ivp-rs
Version: 0.1.2
Classifier: Development Status :: 4 - Beta
Classifier: Intended Audience :: Science/Research
Classifier: License :: OSI Approved :: Apache Software License
Classifier: Programming Language :: Python :: 3
Classifier: Programming Language :: Python :: 3.9
Classifier: Programming Language :: Python :: 3.10
Classifier: Programming Language :: Python :: 3.11
Classifier: Programming Language :: Python :: 3.12
Classifier: Programming Language :: Python :: 3.13
Classifier: Programming Language :: Rust
Classifier: Topic :: Scientific/Engineering :: Mathematics
Requires-Dist: numpy
License-File: LICENSE
Summary: A Rust library for solving initial value problems (IVPs) for ordinary differential equations (ODEs).
Keywords: differential,equations,solve_ivp,ode,ivp
Home-Page: https://github.com/Ryan-D-Gast/ivp
Author-email: "Ryan D. Gast" <ryan.d.gast@gmail.com>
License-Expression: Apache-2.0
Requires-Python: >=3.9
Project-URL: Homepage, https://github.com/Ryan-D-Gast/ivp
Project-URL: Repository, https://github.com/Ryan-D-Gast/ivp
Project-URL: Documentation, https://docs.rs/ivp
